pbot/cli.py
pbot/commands/__init__.py
pbot/commands/init/__init__.py
pbot/commands/init/base.py
pbot/commands/init/github_init.py
pbot/commands/init/python.py
pbot/errors/__init__.py
pbot/errors/sentry.py
pbot/logging/__init__.py
pbot/logging/logger.py
pbot/metrics/__init__.py
pbot/metrics/prometheus.py
pbot_cli-0.1.1.dist-info/entry_points.txt
pbot_cli-0.1.1.dist-info/METADATA
pbot_cli-0.1.1.dist-info/WHEEL
pbot_cli-0.1.1.dist-info/RECORD
