Metadata-Version: 2.3
Name: pbot-cli
Version: 0.1.1
Summary: A CLI tool to bootstrap projects like Python, Angular
License: MIT
Author: Your Name
Author-email: you@example.com
Requires-Python: >=3.10
Classifier: License :: OSI Approved :: MIT License
Classifier: Operating System :: OS Independent
Classifier: Programming Language :: Python :: 3
Classifier: Programming Language :: Python :: 3.10
Classifier: Programming Language :: Python :: 3.11
Classifier: Programming Language :: Python :: 3.12
Classifier: Programming Language :: Python :: 3.13
Requires-Dist: prometheus-client (>=0.22.1,<0.23.0)
Requires-Dist: pyyaml (>=6.0,<7.0)
Requires-Dist: requests (>=2.31.0,<3.0.0)
Requires-Dist: sentry-sdk (>=2.32.0,<3.0.0)
Requires-Dist: typer[all] (>=0.16.0,<0.17.0)
